{"Matt Brash": 3.65, "Tim Herrin": 4.35, "Raisel Iglesias": 3.3, "Mason Miller": 2.78, "Daniel Palencia": 3.86, "Tyler Samaniego": 3.74, "Jos\u00e9 Soriano": 2.2, "Shohei Ohtani": 1.99, "Antonio Senzatela": 2.46, "Louis Varland": 2.71, "Tyler Alexander": 3.16, "Tyler Rogers": 3.64, "Dennis Santana": 3.69, "Kyle Finnegan": 4.43, "Brock Burke": 3.16, "Bradgley Rodriguez": 3.08, "Rico Garcia": 3.66, "Robert Suarez": 2.99, "Huascar Brazob\u00e1n": 3.69, "Brennan Bernardino": 3.42, "Caleb Kilian": 4.18, "John King": 4.14, "Hunter Brown": 3.12, "Daniel Lynch IV": 3.21, "Seth Lugo": 2.27, "Isaac Mattson": 3.49, "Aroldis Chapman": 3.74, "Jacob Latz": 3.42, "Gordon Graceffo": 3.79, "Riley O'Brien": 2.67, "Graham Ashcraft": 3.37, "Jhoan Duran": 3.52, "Chase Shugart": 4.46, "Dylan Lee": 2.85, "Anthony Nunez": 3.76, "Jalen Beeks": 3.62, "Jimmy Herget": 3.18, "Tyler Kinley": 3.66, "Sam Moll": 4.22, "Payton Tolle": 3.73, "Bryan Hudson": 3.59, "Jason Adam": 4.07, "Tyler Phillips": 4.11, "Eduard Bazardo": 3.62, "Matt Gage": 4.42, "Tim Hill": 3.94, "Parker Messick": 2.51, "Cam Schlittler": 1.5, "Blade Tidwell": 4.03, "Justin Wrobleski": 3.03, "Randy V\u00e1squez": 2.51, "Braydon Fisher": 3.69, "Alex Vesia": 3.42, "Bryce Elder": 3.1, "Gregory Soto": 3.38, "Kody Funderburk": 4.8, "Garrett Whitlock": 4.0, "Davis Martin": 3.04, "Jakob Junis": 3.88, "Yohan Ram\u00edrez": 3.64, "Yennier Cano": 3.77, "Jose A. Ferrer": 3.45, "Brooks Raley": 4.05, "Clay Holmes": 4.23, "Nick Martinez": 3.87, "Dylan Cease": 1.5, "Brent Suter": 3.99, "Juan Morillo": 3.55, "Jacob deGrom": 3.22, "Riley Martin": 3.83, "Connor Phillips": 4.64, "Kai-Wei Teng": 4.48, "Shota Imanaga": 2.86, "Hoby Milner": 4.68, "Cade Povich": 4.0, "Brent Headrick": 3.14, "Jovani Mor\u00e1n": 4.35, "Michael King": 3.64, "Landen Roupp": 2.38, "Kyle Freeland": 3.97, "DL Hall": 4.43, "Wandy Peralta": 4.23, "Tony Santillan": 4.43, "Hogan Harris": 4.42, "Joel Kuhnel": 3.66, "Chad Patrick": 4.31, "Ben Brown": 3.02, "Andrew Hoffmann": 5.29, "Pierce Johnson": 3.53, "Tanner Scott": 4.17, "Braxton Ashcraft": 2.39, "Spencer Arrighetti": 4.02, "Tyler Glasnow": 2.22, "Cade Horton": 4.35, "Will Klein": 3.14, "Drew Rasmussen": 4.07, "Yoshinobu Yamamoto": 3.13, "Paul Skenes": 2.86, "Michael Wacha": 3.6, "Casey Mize": 2.93, "Brandon Young": 4.08, "Grant Anderson": 3.45, "Chase Burns": 3.99, "Kevin Gausman": 2.56, "JR Ritchie": 4.65, "Evan Sisk": 3.61, "Will Warren": 2.75, "Aaron Ashby": 2.81, "Tobias Myers": 3.61, "Michael Soroka": 2.67, "Chase Silseth": 4.45, "Sam Bachman": 3.38, "Nolan McLean": 2.34, "Garrett Acton": 3.7, "Brant Hurter": 4.11, "Luis Medina": 4.11, "Mart\u00edn P\u00e9rez": 4.58, "Robbie Ray": 4.21, "Gabe Speier": 3.99, "Grant Wolfram": 3.15, "Tarik Skubal": 1.94, "Edward Cabrera": 3.61, "Cooper Criswell": 4.73, "Steven Okert": 4.05, "Ryan Helsley": 3.45, "Eli Morgan": 4.85, "Chris Sale": 4.38, "Keaton Winn": 3.19, "Emerson Hancock": 3.94, "Max Fried": 2.73, "Erik Sabrowski": 3.19, "Chase Dollander": 3.3, "Connelly Early": 4.14, "Eduardo Rodriguez": 4.96, "Taj Bradley": 3.78, "JT Brubaker": 4.44, "David Morgan": 4.52, "Jesse Scholtens": 3.62, "Cristopher S\u00e1nchez": 2.6, "George Kirby": 3.79, "Orion Kerkering": 4.6, "Richard Lovelady": 4.38, "Nick Mears": 4.08, "Ryan Walker": 3.98, "Sandy Alcantara": 4.07, "Kyle Harrison": 4.24, "Eric Orze": 3.31, "Jack Kochanowicz": 4.1, "Rhett Lowder": 3.24, "Caleb Thielbar": 4.61, "Zac Gallen": 3.55, "Carter Baumler": 4.87, "Jose Franco": 4.27, "Mitch Keller": 3.07, "Ryan Weathers": 3.37, "Grant Taylor": 2.71, "Peter Lambert": 3.18, "Gavin Williams": 4.42, "Carmen Mlodzinski": 2.36, "Lake Bachar": 4.22, "Taylor Clarke": 4.02, "Michael McGreevy": 4.45, "Spencer Miles": 4.18, "Justin Sterner": 3.46, "Jacob Misiorowski": 3.22, "Jack Anderson": 4.16, "David Bednar": 3.32, "Coleman Crow": 3.8, "Robert Garcia": 4.24, "Foster Griffin": 4.9, "Michael Petersen": 3.88, "Tyler Wells": 3.79, "Framber Valdez": 3.77, "Erick Fedde": 4.85, "Tomoyuki Sugano": 4.81, "Albert Su\u00e1rez": 5.33, "Clayton Beeter": 5.17, "Jaden Hill": 4.25, "Kumar Rocker": 3.9, "Cole Sands": 3.97, "Gus Varland": 3.69, "Aaron Bummer": 4.42, "Noah Schultz": 3.7, "Jonathan Lo\u00e1isiga": 3.67, "JoJo Romero": 4.31, "Joey Cantillo": 3.96, "Hunter Gaddis": 4.18, "Zack Wheeler": 3.9, "Grant Holmes": 4.86, "Janson Junk": 3.69, "Patrick Corbin": 4.38, "Kenley Jansen": 4.59, "Keider Montero": 2.16, "Zach Pop": 3.91, "Joe Mantiply": 3.77, "J.T. Ginn": 4.93, "Reynaldo L\u00f3pez": 5.17, "Scott Barlow": 4.82, "Ron Marinaccio": 4.23, "Cole Sulser": 4.23, "Brandon Woodruff": 4.04, "Jeffrey Springs": 4.19, "Bryan Baker": 3.9, "Jonathan Bowlan": 3.48, "Aaron Civale": 3.92, "Enyel De Los Santos": 4.06, "Brad Keller": 4.31, "Peyton Pallette": 4.23, "Jack Perkins": 3.46, "Justin Topa": 4.27, "Bryan Woo": 3.73, "Freddy Peralta": 3.87, "Joe Ryan": 3.19, "Shane McClanahan": 3.27, "Bailey Ober": 3.85, "Logan Webb": 3.57, "Kyle Bradish": 3.46, "Max Meyer": 3.46, "Kevin Ginkel": 3.0, "Mason Montgomery": 3.29, "Mick Abel": 3.04, "Fernando Cruz": 4.76, "Zack Kelly": 4.0, "Erik Miller": 3.36, "Ranger Suarez": 4.03, "Cade Cavalli": 2.8, "Kris Bubic": 3.8, "Reid Detmers": 3.0, "Jack Dreyer": 3.82, "Dean Kremer": 4.78, "Connor Seabold": 4.62, "Sean Burke": 3.97, "Luis Gil": 6.1, "Cade Smith": 3.45, "Brad Lord": 4.6, "Shawn Armstrong": 4.72, "Bryan King": 3.76, "Greg Weissert": 4.52, "Cody Laweryson": 3.8, "Andre Pallante": 4.96, "Sonny Gray": 4.43, "MacKenzie Gore": 4.04, "Abner Uribe": 3.77, "Logan Gilbert": 2.98, "Jordan Hicks": 4.56, "Kevin Kelly": 3.92, "Germ\u00e1n M\u00e1rquez": 5.84, "Emilio Pag\u00e1n": 4.76, "PJ Poulin": 5.51, "Tanner Bibee": 4.62, "Hunter Bigge": 4.84, "Paul Blackburn": 3.84, "Seranthony Dom\u00ednguez": 4.91, "Calvin Faucher": 3.88, "Tyler Holton": 4.66, "Tim Mayza": 4.37, "Sean Newcomb": 3.11, "Nick Pivetta": 2.49, "Paxton Schultz": 4.6, "Paul Sewald": 4.75, "Lucas Sims": 4.47, "Cole Winn": 4.22, "Ryan Yarbrough": 4.55, "Jameson Taillon": 5.99, "Eury P\u00e9rez": 5.02, "Colin Rea": 3.87, "Casey Legumina": 3.71, "Kyle Backhus": 4.17, "Sean Manaea": 3.96, "Matt Strahm": 4.65, "Ryan Thompson": 5.09, "Jacob Webb": 4.69, "Blake Treinen": 4.66, "Matthew Liberatore": 6.36, "Trevor Rogers": 3.69, "George Soriano": 4.37, "Walbert Urena": 4.41, "Emmet Sheehan": 4.09, "Steven Matz": 5.05, "Jake Irvin": 4.08, "Bubba Chandler": 5.59, "Kyle Hart": 3.86, "Edgardo Henriquez": 4.27, "Brady Singer": 4.96, "Jack Leiter": 3.77, "Cole Ragans": 6.03, "John Schreiber": 5.32, "Luis Castillo": 3.58, "Justin Bruihl": 5.19, "Aaron Nola": 4.0, "David Peterson": 3.74, "Shane Baz": 3.67, "Noah Cameron": 4.85, "Jeremiah Estrada": 3.89, "Joe Boyle": 3.49, "Luis Severino": 4.92, "Ryan Borucki": 4.61, "Christian Roa": 5.09, "Lucas Erceg": 4.17, "Andrew Painter": 3.35, "Tyler Mahle": 5.75, "Jack Flaherty": 6.02, "Cody Bolton": 4.47, "Luis Curvelo": 5.06, "Shane Drohan": 4.22, "Mason Fluharty": 3.59, "Andrew Nardi": 4.19, "Mitchell Parker": 4.07, "Luke Weaver": 4.23, "Brandon Williamson": 6.26, "Brandon Pfaadt": 5.02, "Anthony Kay": 6.12, "Kyle Leahy": 5.59, "Jacob Lopez": 6.16, "Walker Buehler": 3.44, "Matthew Boyd": 2.73, "Nathan Eovaldi": 5.64, "Dustin May": 3.92, "Jos\u00e9 Suarez": 3.22, "Connor Brogdon": 4.68, "Jake Woodford": 3.96, "Adrian Morejon": 3.3, "Shaun Anderson": 5.16, "Simeon Woods Richardson": 5.79, "Michael Lorenzen": 4.53, "Justin Lawrence": 4.9, "Jayden Murray": 4.17, "Zach Agnos": 4.1, "Matt Festa": 3.92, "Danny Coulombe": 4.51, "Juan Mejia": 4.07, "Slade Cecconi": 5.92, "Yusei Kikuchi": 3.69, "AJ Blubaugh": 5.21, "Jose Quintana": 5.97, "Mike Burrows": 5.12, "Anthony Bender": 3.87, "Garrett Crochet": 4.3, "Ryan Feltner": 5.53, "Cole Wilcox": 4.23, "Cameron Foster": 4.03, "Roki Sasaki": 6.89, "Chris Paddack": 4.59, "Ryan Zeferjahn": 3.35, "Angel Zerpa": 4.79, "Hunter Barco": 5.58, "Didier Fuentes": 3.81, "Cole Henry": 4.41, "Cal Quantrill": 4.13, "Brandon Sproat": 5.78, "Ryan Weiss": 5.94, "Andr\u00e9s Mu\u00f1oz": 4.06, "Tommy Nance": 3.74, "Andrew Abbott": 4.95, "Drew Anderson": 4.84, "Chris Bassitt": 5.95, "Tanner Gordon": 5.12, "Eric Lauer": 6.25, "Jordan Leasure": 5.72, "Lance McCullers Jr.": 5.03, "Will Vest": 4.04, "Ken Waldichuk": 6.02, "Jes\u00fas Luzardo": 3.21, "Mark Leiter Jr.": 4.39, "Ryne Nelson": 4.86, "Yoendrys G\u00f3mez": 6.5, "Mason Englert": 5.43, "Luis Garc\u00eda": 3.88, "Chris Martin": 4.04, "Joel Payamps": 4.8, "Tanner Banks": 4.19, "Drew Pomeranz": 4.47, "Pete Fairbanks": 3.57, "Tatsuya Imai": 4.25, "Taylor Rogers": 3.89, "Osvaldo Bido": 5.4, "Ryan Watson": 5.23, "Jake Bird": 3.95, "Adrian Houser": 5.09, "Jos\u00e9 Alvarado": 3.77, "Camilo Doval": 4.43, "Zack Littell": 8.58, "Javier Assad": 4.78, "Valente Bellozo": 6.28, "Jeff Hoffman": 3.84, "Alex Lange": 4.28, "Victor Vodnik": 5.0, "Cionel P\u00e9rez": 5.29, "Andrew Morris": 3.53, "Ian Seymour": 3.59, "Griffin Jax": 5.44, "Trevor Megill": 3.64, "J.P. France": 4.86, "Elvis Alvarado": 4.45, "Ryne Stanek": 4.36, "Miles Mikolas": 6.74, "Jos\u00e9 Urquidy": 4.24, "Kyle Nicolas": 5.43, "Kodai Senga": 4.97, "Luinder Avila": 4.49, "Brayan Bello": 7.76, "Taijuan Walker": 7.45, "Anthony Banda": 4.32, "Merrill Kelly": 6.09, "Nick Sandlin": 4.63, "Max Scherzer": 7.31, "Enmanuel De Jesus": 3.88, "Jordan Romano": 4.28, "Devin Williams": 4.13, "Kolby Allard": 4.65, "Edwin D\u00edaz": 4.41, "Chris Murphy": 4.61, "Matt Svanson": 5.78, "Shane Smith": 4.71, "Colton Gordon": 6.02, "Luis Morales": 5.64, "Matt Waldron": 4.93, "Cristian Javier": 5.86, "Bryan Abreu": 5.83, "Steven Cruz": 5.2}