{"New York Yankees": 0.36, "Atlanta Braves": 0.3077, "Los Angeles Dodgers": 0.08, "Seattle Mariners": 0.4231, "Chicago Cubs": 0.4, "Pittsburgh Pirates": 0.6, "Texas Rangers": 0.28, "Cincinnati Reds": 0.36, "San Diego Padres": 0.2, "Detroit Tigers": 0.3846, "San Francisco Giants": 0.28, "Miami Marlins": 0.6, "Milwaukee Brewers": 0.2917, "Los Angeles Angels": 0.5385, "Baltimore Orioles": 0.64, "Cleveland Guardians": 0.3462, "Minnesota Twins": 0.6, "New York Mets": 0.36, "Boston Red Sox": 0.28, "Colorado Rockies": 0.5, "Arizona Diamondbacks": 0.6, "Toronto Blue Jays": 0.5833, "Athletics": 0.16, "Tampa Bay Rays": 0.625, "Kansas City Royals": 0.32, "St. Louis Cardinals": 0.3333, "Chicago White Sox": 0.36, "Philadelphia Phillies": 0.56, "Washington Nationals": 0.5769, "Houston Astros": 0.1538, "__league_avg__": 0.4032}