{"Los Angeles Dodgers": 123, "Atlanta Braves": 114, "Houston Astros": 112, "Washington Nationals": 106, "Tampa Bay Rays": 102, "Miami Marlins": 104, "Pittsburgh Pirates": 106, "Chicago Cubs": 106, "San Francisco Giants": 94, "Toronto Blue Jays": 97, "Arizona Diamondbacks": 98, "Texas Rangers": 101, "Detroit Tigers": 98, "Baltimore Orioles": 101, "Milwaukee Brewers": 102, "Boston Red Sox": 94, "San Diego Padres": 98, "St. Louis Cardinals": 100, "Colorado Rockies": 96, "Los Angeles Angels": 107, "Athletics": 94, "Cleveland Guardians": 99, "New York Mets": 90, "Minnesota Twins": 102, "Philadelphia Phillies": 97, "Kansas City Royals": 91, "New York Yankees": 99, "Seattle Mariners": 92, "Chicago White Sox": 89, "Cincinnati Reds": 88}