{
  "Bill Miller": {
    "run_factor": 1.1582,
    "games": 9
  },
  "Adrian Johnson": {
    "run_factor": 1.3408,
    "games": 6
  },
  "Mark Wegner": {
    "run_factor": 1.2747,
    "games": 8
  },
  "Alan Porter": {
    "run_factor": 0.9348,
    "games": 8
  },
  "Laz Diaz": {
    "run_factor": 1.0056,
    "games": 8
  },
  "Dan Iassogna": {
    "run_factor": 0.9773,
    "games": 8
  },
  "Chris Conroy": {
    "run_factor": 0.7284,
    "games": 7
  },
  "Alfonso M\u00e1rquez": {
    "run_factor": 1.0622,
    "games": 8
  },
  "Chris Guccione": {
    "run_factor": 0.955,
    "games": 7
  },
  "James Hoye": {
    "run_factor": 1.0521,
    "games": 7
  },
  "Andy Fletcher": {
    "run_factor": 1.5377,
    "games": 7
  },
  "Lance Barksdale": {
    "run_factor": 0.9773,
    "games": 8
  },
  "Chad Fairchild": {
    "run_factor": 1.0198,
    "games": 7
  },
  "Marvin Hudson": {
    "run_factor": 0.5665,
    "games": 7
  },
  "Jordan Baker": {
    "run_factor": 0.6151,
    "games": 7
  },
  "Doug Eddings": {
    "run_factor": 1.3435,
    "games": 7
  },
  "John Tumpane": {
    "run_factor": 0.8741,
    "games": 7
  },
  "Lance Barrett": {
    "run_factor": 1.0449,
    "games": 9
  },
  "Will Little": {
    "run_factor": 1.1472,
    "games": 8
  },
  "Cory Blaser": {
    "run_factor": 0.661,
    "games": 6
  },
  "David Rackley": {
    "run_factor": 1.0056,
    "games": 8
  },
  "Jim Wolf": {
    "run_factor": 1.1557,
    "games": 5
  },
  "Tripp Gibson": {
    "run_factor": 1.0056,
    "games": 8
  },
  "Brian O'Nora": {
    "run_factor": 1.0198,
    "games": 7
  },
  "D.J. Reyburn": {
    "run_factor": 0.9226,
    "games": 7
  },
  "CB Bucknor": {
    "run_factor": 1.1897,
    "games": 2
  },
  "Quinn Wolcott": {
    "run_factor": 0.9064,
    "games": 8
  },
  "Rob Drake": {
    "run_factor": 1.0198,
    "games": 8
  },
  "Ben May": {
    "run_factor": 1.2237,
    "games": 5
  },
  "Bruce Dreckman": {
    "run_factor": 0.9064,
    "games": 9
  },
  "Mike Muchlinski": {
    "run_factor": 0.9773,
    "games": 8
  },
  "Chad Whitson": {
    "run_factor": 0.9388,
    "games": 7
  },
  "Malachi Moore": {
    "run_factor": 0.982,
    "games": 9
  },
  "Jansen Visconti": {
    "run_factor": 0.8876,
    "games": 6
  },
  "Ryan Additon": {
    "run_factor": 1.0036,
    "games": 7
  },
  "Chris Segal": {
    "run_factor": 0.9226,
    "games": 7
  },
  "Sean Barber": {
    "run_factor": 0.9206,
    "games": 8
  },
  "Gabe Morales": {
    "run_factor": 0.9388,
    "games": 7
  },
  "Ryan Blakney": {
    "run_factor": 0.8255,
    "games": 7
  },
  "Adam Beck": {
    "run_factor": 1.1978,
    "games": 7
  },
  "Ramon De Jesus": {
    "run_factor": 0.7648,
    "games": 4
  },
  "Stu Scheurwater": {
    "run_factor": 0.7507,
    "games": 8
  },
  "Brennan Miller": {
    "run_factor": 1.0845,
    "games": 7
  },
  "Carlos Torres": {
    "run_factor": 1.0622,
    "games": 8
  },
  "Nestor Ceja": {
    "run_factor": 0.9914,
    "games": 8
  },
  "Roberto Ortiz": {
    "run_factor": 1.2464,
    "games": 7
  },
  "Ryan Wills": {
    "run_factor": 0.6151,
    "games": 7
  },
  "Alex Tosi": {
    "run_factor": 0.6313,
    "games": 7
  },
  "Ron Kulpa": {
    "run_factor": 1.303,
    "games": 2
  },
  "Junior Valentine": {
    "run_factor": 0.8309,
    "games": 6
  },
  "Nick Mahrley": {
    "run_factor": 1.1557,
    "games": 5
  },
  "Emil Jimenez": {
    "run_factor": 1.4447,
    "games": 4
  },
  "Erich Bacchus": {
    "run_factor": 1.4406,
    "games": 7
  },
  "Dan Bellino": {
    "run_factor": 1.0339,
    "games": 8
  },
  "Charlie Ramos": {
    "run_factor": 0.7931,
    "games": 8
  },
  "Jeremie Rehak": {
    "run_factor": 1.1519,
    "games": 6
  },
  "Vic Carapazza": {
    "run_factor": 1.1217,
    "games": 10
  },
  "Nate Tomlinson": {
    "run_factor": 1.3172,
    "games": 8
  },
  "Mike Estabrook": {
    "run_factor": 0.9568,
    "games": 9
  },
  "Todd Tichenor": {
    "run_factor": 0.8356,
    "games": 8
  },
  "Paul Clemons": {
    "run_factor": 0.8309,
    "games": 6
  },
  "Scott Barry": {
    "run_factor": 0.955,
    "games": 7
  },
  "Mark Ripperger": {
    "run_factor": 0.8498,
    "games": 8
  },
  "Hunter Wendelstedt": {
    "run_factor": 0.9631,
    "games": 8
  },
  "Shane Livensparger": {
    "run_factor": 1.1007,
    "games": 7
  },
  "Manny Gonzalez": {
    "run_factor": 1.0622,
    "games": 8
  },
  "Nic Lentz": {
    "run_factor": 1.0056,
    "games": 8
  },
  "Adam Hamari": {
    "run_factor": 1.1007,
    "games": 7
  },
  "Tom Hanahan": {
    "run_factor": 1.1492,
    "games": 7
  },
  "Clint Vondrak": {
    "run_factor": 0.7446,
    "games": 7
  },
  "Dan Merzel": {
    "run_factor": 1.1331,
    "games": 6
  },
  "Edwin Moscoso": {
    "run_factor": 1.0198,
    "games": 7
  },
  "Willie Traynor": {
    "run_factor": 1.5215,
    "games": 7
  },
  "James Jean": {
    "run_factor": 1.2917,
    "games": 5
  },
  "Edwin Jimenez": {
    "run_factor": 0.9914,
    "games": 4
  },
  "Brian Walsh": {
    "run_factor": 0.9064,
    "games": 6
  },
  "John Libka": {
    "run_factor": 0.7122,
    "games": 7
  },
  "Alex MacKay": {
    "run_factor": 0.9442,
    "games": 6
  },
  "Derek Thomas": {
    "run_factor": 1.3823,
    "games": 5
  },
  "Brock Ballou": {
    "run_factor": 0.8611,
    "games": 5
  },
  "Steven Jaschinski": {
    "run_factor": 0.9064,
    "games": 2
  },
  "Dexter Kelley": {
    "run_factor": 1.1047,
    "games": 4
  },
  "Austin Jones": {
    "run_factor": 0.8838,
    "games": 5
  },
  "John Bacon": {
    "run_factor": 0.6798,
    "games": 5
  },
  "Jen Pawol": {
    "run_factor": 1.6996,
    "games": 1
  },
  "Tyler Jones": {
    "run_factor": 1.2086,
    "games": 3
  },
  "Felix Neon": {
    "run_factor": 0.5665,
    "games": 1
  },
  "Jacob Metz": {
    "run_factor": 0.7082,
    "games": 4
  },
  "Louie Krupa": {
    "run_factor": 0.17,
    "games": 2
  },
  "Jonathan Parra": {
    "run_factor": 0.4532,
    "games": 1
  }
}